russe_pack/__init__.py
russe_pack/get_episodes.py
russe_pack-0.1.0.dist-info/entry_points.txt
russe_pack-0.1.0.dist-info/WHEEL
russe_pack-0.1.0.dist-info/METADATA
russe_pack-0.1.0.dist-info/RECORD
